nano_duration/__init__.py
nano_duration/calendar/__init__.py
nano_duration/duration.py
nano_duration/exceptions.py
nano_duration/iso_duration.py
nano_duration-2.0.1.dist-info/METADATA
nano_duration-2.0.1.dist-info/WHEEL
nano_duration-2.0.1.dist-info/RECORD
