Metadata-Version: 2.3
Name: nano_duration
Version: 2.0.1
Summary: 
Author: xenups
Author-email: amirhossein@void-star.co
Requires-Python: >=3.10,<4.0
Classifier: Programming Language :: Python :: 3
Classifier: Programming Language :: Python :: 3.10
Classifier: Programming Language :: Python :: 3.11
Classifier: Programming Language :: Python :: 3.12
Classifier: Programming Language :: Python :: 3.13
Requires-Dist: pytest (>=7.2.0,<8.0.0)
Requires-Dist: pytest-cov (>=4.0.0,<5.0.0)
Requires-Dist: pytest-env (>=0.8.1,<0.9.0)
Requires-Dist: setuptools (>=80.9.0,<81.0.0)
